{
	"image": "dan.png",
	"config": "dan.plist",
	"stageHeight": 400,
	"stageWidth": 550,
	"version": 1,
	"groups": {
		"rank.dan_/@RewardItem": [
			{
				"x": 0,
				"y": 0,
				"width": 176,
				"height": 178,
				"scaleX": 1,
				"scaleY": 1,
				"skewX": 0,
				"skewY": 0,
				"rotation": 0,
				"index": 0,
				"id": "bg",
				"image": "rank.dan_/assert/d/未命名文件夹 1/未命名文件夹 2/元件 4",
				"type": 0,
				"scalingGrid": false
			},
			{
				"x": 30,
				"y": 34,
				"width": 100,
				"height": 100,
				"scaleX": 12.499923706054688,
				"scaleY": 12.499923706054688,
				"skewX": 0,
				"skewY": 0,
				"rotation": 0,
				"index": 1,
				"id": "holder",
				"image": "ui_commons/ui_fontsize_rect",
				"type": 0,
				"scalingGrid": false
			},
			{
				"scaleX": 0.999786376953125,
				"scaleY": 0.9998016357421875,
				"skewX": 0,
				"skewY": 0,
				"rotation": 0,
				"lineType": "single line",
				"maxCharacters": 0,
				"textType": "dynamic",
				"face": "Segoe UI Symbol",
				"size": 40,
				"fillColor": "#ffffff",
				"alignment": "left",
				"letterSpacing": 0,
				"x": 104.55,
				"y": 96.3,
				"width": 44.1,
				"height": 57.2,
				"index": 2,
				"id": "num",
				"type": 1
			},
			{
				"x": 105,
				"y": 96,
				"width": 44.1,
				"height": 57.2,
				"scaleX": 5.5124969482421875,
				"scaleY": 7.149993896484375,
				"skewX": 0,
				"skewY": 0,
				"rotation": 0,
				"index": 3,
				"id": "numSize",
				"image": "ui_commons/ui_fontsize_rect",
				"type": 0,
				"scalingGrid": false
			}
		],
		"rank.dan_/assert/as/元件 4": [
			{
				"x": 0,
				"y": 0,
				"width": 68,
				"height": 61,
				"scaleX": 1,
				"scaleY": 1,
				"skewX": 0,
				"skewY": 0,
				"rotation": 0,
				"index": 0,
				"id": "1",
				"image": "rank.dan_/assert/as/元件 2",
				"type": 0,
				"scalingGrid": false
			},
			{
				"x": 272,
				"y": 0,
				"width": 68,
				"height": 61,
				"scaleX": 1,
				"scaleY": 1,
				"skewX": 0,
				"skewY": 0,
				"rotation": 0,
				"index": 1,
				"id": "2",
				"image": "rank.dan_/assert/as/元件 3",
				"type": 0,
				"scalingGrid": false
			}
		],
		"rank.dan_/assert/as/元件 86": [
			{
				"x": 287,
				"y": 0,
				"width": 75,
				"height": 67,
				"scaleX": 1,
				"scaleY": 1,
				"skewX": 0,
				"skewY": 0,
				"rotation": 0,
				"index": 0,
				"id": "1",
				"image": "rank.dan_/assert/as/元件 84",
				"type": 0,
				"scalingGrid": false
			},
			{
				"x": 0,
				"y": 0,
				"width": 76,
				"height": 67,
				"scaleX": 1,
				"scaleY": 1,
				"skewX": 0,
				"skewY": 0,
				"rotation": 0,
				"index": 1,
				"id": "1_m_1",
				"image": "rank.dan_/assert/as/元件 85",
				"type": 0,
				"scalingGrid": false
			}
		],
		"rank.dan_/assert/as/元件 89": [
			{
				"x": 0,
				"y": 0,
				"width": 68,
				"height": 60,
				"scaleX": 1,
				"scaleY": 1,
				"skewX": 0,
				"skewY": 0,
				"rotation": 0,
				"index": 0,
				"id": "2",
				"image": "rank.dan_/assert/as/元件 87",
				"type": 0,
				"scalingGrid": false
			},
			{
				"x": 274,
				"y": 0,
				"width": 67,
				"height": 60,
				"scaleX": 1,
				"scaleY": 1,
				"skewX": 0,
				"skewY": 0,
				"rotation": 0,
				"index": 1,
				"id": "1",
				"image": "rank.dan_/assert/as/元件 88",
				"type": 0,
				"scalingGrid": false
			}
		],
		"rank.dan_/assert/d/@HBox": [
			{
				"x": 0,
				"y": 0,
				"width": 534.85,
				"height": 178,
				"scaleX": 66.85414123535156,
				"scaleY": 22.2530517578125,
				"skewX": 0,
				"skewY": 0,
				"rotation": 0,
				"index": 0,
				"id": "size",
				"image": "ui_commons/ui_fontsize_rect",
				"type": 0,
				"scalingGrid": false
			},
			{
				"x": 352,
				"y": 7,
				"width": 176,
				"height": 178,
				"scaleX": 1,
				"scaleY": 1,
				"skewX": 0,
				"skewY": 0,
				"rotation": 0,
				"index": 1,
				"id": "item3",
				"image": "rank.dan_/@RewardItem",
				"type": 2,
				"scalingGrid": false
			},
			{
				"x": 190,
				"y": 7,
				"width": 176,
				"height": 178,
				"scaleX": 1,
				"scaleY": 1,
				"skewX": 0,
				"skewY": 0,
				"rotation": 0,
				"index": 2,
				"id": "item2",
				"image": "rank.dan_/@RewardItem",
				"type": 2,
				"scalingGrid": false
			},
			{
				"x": 23,
				"y": 7,
				"width": 176,
				"height": 178,
				"scaleX": 1,
				"scaleY": 1,
				"skewX": 0,
				"skewY": 0,
				"rotation": 0,
				"index": 3,
				"id": "item1",
				"image": "rank.dan_/@RewardItem",
				"type": 2,
				"scalingGrid": false
			}
		],
		"rank.dan_/assert/d/未命名文件夹 1/未命名文件夹 2/dsa": [
			{
				"x": 0,
				"y": 0,
				"width": 240,
				"height": 46.25,
				"scaleX": 30,
				"scaleY": 5.7789154052734375,
				"skewX": 0,
				"skewY": 0,
				"rotation": 0,
				"index": 0,
				"id": "hit_area",
				"image": "ui_commons/ui_fontsize_rect",
				"type": 0,
				"scalingGrid": false
			},
			{
				"scaleX": 0.9999847412109375,
				"scaleY": 0.999969482421875,
				"skewX": 0,
				"skewY": 0,
				"rotation": 0,
				"lineType": "single line",
				"maxCharacters": 0,
				"textType": "static",
				"face": "微软雅黑",
				"size": 20,
				"fillColor": "#663300",
				"alignment": "left",
				"letterSpacing": 0,
				"x": 0,
				"y": 7.5,
				"width": 236.95,
				"height": 30.4,
				"index": 1,
				"id": "key",
				"type": 1
			},
			{
				"scaleX": 1,
				"scaleY": 1,
				"skewX": 0,
				"skewY": 0,
				"rotation": 0,
				"lineType": "single line",
				"maxCharacters": 0,
				"textType": "dynamic",
				"face": "微软雅黑",
				"size": 40,
				"fillColor": "#cc6600",
				"alignment": "left",
				"letterSpacing": 0,
				"x": 157.25,
				"y": -0.8,
				"width": 73.7,
				"height": 56.75,
				"index": 2,
				"id": "value",
				"type": 1
			}
		],
		"rank.dan_/assert/n.race.rank.assert/@VScroll": [
			{
				"x": 0,
				"y": 0,
				"width": 239.3,
				"height": 246.4,
				"scaleX": 29.911758422851562,
				"scaleY": 30.80084228515625,
				"skewX": 0,
				"skewY": 0,
				"rotation": 0,
				"index": 0,
				"id": "size",
				"image": "ui_commons/ui_fontsize_rect",
				"type": 0,
				"scalingGrid": false
			}
		],
		"rank.dan_/assert/n.race.rank.assert/asdwq/元件 2": [
			{
				"x": 0,
				"y": 0,
				"width": 279,
				"height": 90,
				"scaleX": 1,
				"scaleY": 1,
				"skewX": 0,
				"skewY": 0,
				"rotation": 0,
				"index": 0,
				"id": "图层 1",
				"image": "rank.dan_/assert/n.race.rank.assert/asdwq/元件 1",
				"type": 0,
				"scalingGrid": false
			}
		],
		"rank.dan_/assert/n.race.rank.assert/assert/4th.set.niu/noClip@Page": [
			{
				"x": 0,
				"y": 0,
				"width": 720,
				"height": 1280,
				"scaleX": 89.99928283691406,
				"scaleY": 159.9993896484375,
				"skewX": 0,
				"skewY": 0,
				"rotation": 0,
				"index": 0,
				"id": "size",
				"image": "ui_commons/ui_fontsize_rect",
				"type": 0,
				"scalingGrid": false
			},
			{
				"x": 0,
				"y": 0,
				"width": 720,
				"height": 1280,
				"scaleX": 1,
				"scaleY": 1,
				"skewX": 0,
				"skewY": 0,
				"rotation": 0,
				"index": 1,
				"id": "page1",
				"image": "rank.dan_/Page3",
				"type": 2,
				"scalingGrid": false
			},
			{
				"x": 0,
				"y": 0,
				"width": 720,
				"height": 1280,
				"scaleX": 1,
				"scaleY": 1,
				"skewX": 0,
				"skewY": 0,
				"rotation": 0,
				"index": 2,
				"id": "page2",
				"image": "rank.dan_/Page3",
				"type": 2,
				"scalingGrid": false
			},
			{
				"x": 0,
				"y": 0,
				"width": 720,
				"height": 1280,
				"scaleX": 1,
				"scaleY": 1,
				"skewX": 0,
				"skewY": 0,
				"rotation": 0,
				"index": 3,
				"id": "page3",
				"image": "rank.dan_/Page3",
				"type": 2,
				"scalingGrid": false
			},
			{
				"x": 0,
				"y": 0,
				"width": 720,
				"height": 1280,
				"scaleX": 1,
				"scaleY": 1,
				"skewX": 0,
				"skewY": 0,
				"rotation": 0,
				"index": 4,
				"id": "page4",
				"image": "rank.dan_/Page2",
				"type": 2,
				"scalingGrid": false
			},
			{
				"x": 0,
				"y": 0,
				"width": 720,
				"height": 1280,
				"scaleX": 1,
				"scaleY": 1,
				"skewX": 0,
				"skewY": 0,
				"rotation": 0,
				"index": 5,
				"id": "page5",
				"image": "rank.dan_/Page2",
				"type": 2,
				"scalingGrid": false
			},
			{
				"x": 0,
				"y": 0,
				"width": 720,
				"height": 1280,
				"scaleX": 1,
				"scaleY": 1,
				"skewX": 0,
				"skewY": 0,
				"rotation": 0,
				"index": 6,
				"id": "page6",
				"image": "rank.dan_/Page2",
				"type": 2,
				"scalingGrid": false
			},
			{
				"x": 0,
				"y": 0,
				"width": 720,
				"height": 1280,
				"scaleX": 1,
				"scaleY": 1,
				"skewX": 0,
				"skewY": 0,
				"rotation": 0,
				"index": 7,
				"id": "page7",
				"image": "rank.dan_/Page1",
				"type": 2,
				"scalingGrid": false
			},
			{
				"x": 0,
				"y": 0,
				"width": 720,
				"height": 1280,
				"scaleX": 1,
				"scaleY": 1,
				"skewX": 0,
				"skewY": 0,
				"rotation": 0,
				"index": 8,
				"id": "page8",
				"image": "rank.dan_/Page1",
				"type": 2,
				"scalingGrid": false
			},
			{
				"x": 0,
				"y": 0,
				"width": 720,
				"height": 1280,
				"scaleX": 1,
				"scaleY": 1,
				"skewX": 0,
				"skewY": 0,
				"rotation": 0,
				"index": 9,
				"id": "page9",
				"image": "rank.dan_/Page1",
				"type": 2,
				"scalingGrid": false
			},
			{
				"x": 0,
				"y": 0,
				"width": 720,
				"height": 1280,
				"scaleX": 1,
				"scaleY": 1,
				"skewX": 0,
				"skewY": 0,
				"rotation": 0,
				"index": 10,
				"id": "page10",
				"image": "rank.dan_/Page10",
				"type": 2,
				"scalingGrid": false
			}
		],
		"rank.dan_/Page3": [
			{
				"x": 0,
				"y": 0,
				"width": 720,
				"height": 1280,
				"scaleX": 90,
				"scaleY": 160,
				"skewX": 0,
				"skewY": 0,
				"rotation": 0,
				"index": 0,
				"id": "hit_area",
				"image": "ui_commons/ui_fontsize_rect",
				"type": 0,
				"scalingGrid": false
			},
			{
				"x": 232,
				"y": 145,
				"width": 259,
				"height": 161,
				"scaleX": 1,
				"scaleY": 1,
				"skewX": 0,
				"skewY": 0,
				"rotation": 0,
				"index": 1,
				"id": "animalBG",
				"image": "rank.dan_/assert/as/元件 5",
				"type": 0,
				"scalingGrid": false
			},
			{
				"x": 34,
				"y": 278,
				"width": 620.75,
				"height": 731.95,
				"scaleX": 1,
				"scaleY": 1,
				"skewX": 0,
				"skewY": 0,
				"rotation": 0,
				"index": 2,
				"id": "bg",
				"image": "rank.dan_/assert/n.race.rank.assert/assert/元件 7",
				"type": 2,
				"scalingGrid": false
			},
			{
				"x": 476,
				"y": 312,
				"width": 74,
				"height": 72,
				"scaleX": 1,
				"scaleY": 1,
				"skewX": 0,
				"skewY": 0,
				"rotation": 0,
				"index": 3,
				"id": "descBtn",
				"image": "rank.dan_/assert/n.race.rank.assert/assert/desc@Button",
				"type": 2,
				"scalingGrid": false
			},
			{
				"scaleX": 1,
				"scaleY": 1,
				"skewX": 0,
				"skewY": 0,
				"rotation": 0,
				"lineType": "single line",
				"maxCharacters": 0,
				"textType": "dynamic",
				"face": "微软雅黑",
				"size": 50,
				"fillColor": "#ffff66",
				"alignment": "center",
				"letterSpacing": 0,
				"x": 199.05,
				"y": 300.4,
				"width": 316.2,
				"height": 70,
				"index": 4,
				"id": "title",
				"type": 1
			},
			{
				"x": 78,
				"y": 767,
				"width": 566,
				"height": 223,
				"scaleX": 3.7733154296875,
				"scaleY": 1.4866180419921875,
				"skewX": 0,
				"skewY": 0,
				"rotation": 0,
				"index": 5,
				"id": "bg6",
				"image": "rank.dan_/assert/d/未命名文件夹 1/未命名文件夹 2/元件 1",
				"type": 0,
				"scalingGrid": true
			},
			{
				"x": 89,
				"y": 810,
				"width": 534.85,
				"height": 184.65,
				"scaleX": 1,
				"scaleY": 1,
				"skewX": 0,
				"skewY": 0,
				"rotation": 0,
				"index": 6,
				"id": "hbox",
				"image": "rank.dan_/assert/d/@HBox",
				"type": 2,
				"scalingGrid": false
			},
			{
				"x": 283,
				"y": 858,
				"width": 154,
				"height": 38,
				"scaleX": 1,
				"scaleY": 1,
				"skewX": 0,
				"skewY": 0,
				"rotation": 0,
				"index": 7,
				"id": "rewarded",
				"image": "rank.dan_/assert/dsa/未命名文件夹 2/元件 84",
				"type": 0,
				"scalingGrid": false
			},
			{
				"scaleX": 0.9999847412109375,
				"scaleY": 0.9999542236328125,
				"skewX": 0,
				"skewY": 0,
				"rotation": 0,
				"lineType": "single line",
				"maxCharacters": 0,
				"textType": "static",
				"face": "微软雅黑",
				"size": 26,
				"fillColor": "#663300",
				"alignment": "center",
				"letterSpacing": 0,
				"x": 83,
				"y": 777.75,
				"width": 547.95,
				"height": 38.3,
				"index": 8,
				"id": "label",
				"type": 1
			},
			{
				"x": 75,
				"y": 407,
				"width": 282,
				"height": 350.05,
				"scaleX": 1.8800048828125,
				"scaleY": 2.333740234375,
				"skewX": 0,
				"skewY": 0,
				"rotation": 0,
				"index": 9,
				"id": "bg21",
				"image": "rank.dan_/assert/n.race.rank.assert/assert/重复项目文件夹/元件 1",
				"type": 0,
				"scalingGrid": true
			},
			{
				"x": 362,
				"y": 407,
				"width": 282,
				"height": 350.05,
				"scaleX": 1.8800048828125,
				"scaleY": 2.333740234375,
				"skewX": 0,
				"skewY": 0,
				"rotation": 0,
				"index": 10,
				"id": "bg22",
				"image": "rank.dan_/assert/n.race.rank.assert/assert/重复项目文件夹/元件 1",
				"type": 0,
				"scalingGrid": true
			},
			{
				"x": 133,
				"y": 421,
				"width": 168,
				"height": 54,
				"scaleX": 1,
				"scaleY": 1,
				"skewX": 0,
				"skewY": 0,
				"rotation": 0,
				"index": 11,
				"id": "title21",
				"image": "rank.dan_/assert/n.race.rank.assert/assert/元件 5",
				"type": 0,
				"scalingGrid": false
			},
			{
				"x": 423,
				"y": 421,
				"width": 168,
				"height": 54,
				"scaleX": 1,
				"scaleY": 1,
				"skewX": 0,
				"skewY": 0,
				"rotation": 0,
				"index": 12,
				"id": "title22",
				"image": "rank.dan_/assert/n.race.rank.assert/assert/元件 83",
				"type": 0,
				"scalingGrid": false
			},
			{
				"x": 94,
				"y": 485,
				"width": 253.5,
				"height": 313.8,
				"scaleX": 1,
				"scaleY": 1,
				"skewX": 0,
				"skewY": 0,
				"rotation": 0,
				"index": 13,
				"id": "leftContent",
				"image": "rank.dan_/assert/n.race.rank.assert/left@VScroll",
				"type": 2,
				"scalingGrid": false
			},
			{
				"x": 380,
				"y": 485,
				"width": 239.3,
				"height": 246.4,
				"scaleX": 1,
				"scaleY": 1,
				"skewX": 0,
				"skewY": 0,
				"rotation": 0,
				"index": 14,
				"id": "rightContent",
				"image": "rank.dan_/assert/n.race.rank.assert/@VScroll",
				"type": 2,
				"scalingGrid": false
			},
			{
				"x": 50,
				"y": 291,
				"width": 616,
				"height": 718,
				"scaleX": 5.133331298828125,
				"scaleY": 5.98333740234375,
				"skewX": 0,
				"skewY": 0,
				"rotation": 0,
				"index": 15,
				"id": "darkLayer",
				"image": "rank.dan_/assert/dsa/未命名文件夹 2/重复项目文件夹/21",
				"type": 0,
				"scalingGrid": true
			},
			{
				"x": 611,
				"y": 308,
				"width": 72.45,
				"height": 67.85,
				"scaleX": 1,
				"scaleY": 1,
				"skewX": 0,
				"skewY": 0,
				"rotation": 0,
				"index": 16,
				"id": "closeBtn",
				"image": "rank.dan_/assert/n.race.rank.assert/assert/c@CloseBtn",
				"type": 2,
				"scalingGrid": false
			},
			{
				"x": 296,
				"y": 365,
				"width": 134,
				"height": 38,
				"scaleX": 1,
				"scaleY": 1,
				"skewX": 0,
				"skewY": 0,
				"rotation": 0,
				"index": 17,
				"id": "lock",
				"image": "rank.dan_/assert/dsa/未命名文件夹 2/元件 1",
				"type": 0,
				"scalingGrid": false
			},
			{
				"x": 193,
				"y": 268,
				"width": 340.75,
				"height": 60.1,
				"scaleX": 1,
				"scaleY": 1,
				"skewX": 0,
				"skewY": 0,
				"rotation": 0,
				"index": 18,
				"id": "animalFG",
				"image": "rank.dan_/assert/as/元件 89",
				"type": 2,
				"scalingGrid": false
			}
		],
		"rank.dan_/assert/n.race.rank.assert/assert/元件 7": [
			{
				"x": 14,
				"y": 13,
				"width": 620.75,
				"height": 731.95,
				"scaleX": 4.13848876953125,
				"scaleY": 4.8795166015625,
				"skewX": 0,
				"skewY": 0,
				"rotation": 0,
				"index": 0,
				"id": "bg",
				"image": "rank.dan_/zhou.rank.race/cell/bg",
				"type": 0,
				"scalingGrid": true
			},
			{
				"x": 22,
				"y": 20,
				"width": 603,
				"height": 698.45,
				"scaleX": 3.7926025390625,
				"scaleY": 5.3315277099609375,
				"skewX": 0,
				"skewY": 0,
				"rotation": 0,
				"index": 1,
				"id": "wen",
				"image": "rank.dan_/zhou.rank.race/cell/bgwen",
				"type": 0,
				"scalingGrid": false
			}
		],
		"rank.dan_/assert/n.race.rank.assert/assert/desc@Button": [
			{
				"x": -20,
				"y": -14,
				"width": 74,
				"height": 72,
				"scaleX": 9.25,
				"scaleY": 9,
				"skewX": 0,
				"skewY": 0,
				"rotation": 0,
				"index": 0,
				"id": "hit_area",
				"image": "ui_commons/ui_fontsize_rect",
				"type": 0,
				"scalingGrid": false
			},
			{
				"x": 0,
				"y": 0,
				"width": 46,
				"height": 52,
				"scaleX": 1,
				"scaleY": 1,
				"skewX": 0,
				"skewY": 0,
				"rotation": 0,
				"index": 1,
				"id": "图层 1",
				"image": "rank.dan_/assert/n.race.rank.assert/assert/元件 8",
				"type": 0,
				"scalingGrid": false
			}
		],
		"rank.dan_/assert/n.race.rank.assert/left@VScroll": [
			{
				"x": 0,
				"y": 0,
				"width": 253.5,
				"height": 246,
				"scaleX": 31.686660766601562,
				"scaleY": 30.75054931640625,
				"skewX": 0,
				"skewY": 0,
				"rotation": 0,
				"index": 0,
				"id": "size",
				"image": "ui_commons/ui_fontsize_rect",
				"type": 0,
				"scalingGrid": false
			},
			{
				"x": 0,
				"y": 7,
				"width": 240,
				"height": 56.75,
				"scaleX": 1,
				"scaleY": 1,
				"skewX": 0,
				"skewY": 0,
				"rotation": 0,
				"index": 1,
				"id": "item1",
				"image": "rank.dan_/assert/d/未命名文件夹 1/未命名文件夹 2/dsa",
				"type": 2,
				"scalingGrid": false
			},
			{
				"x": 0,
				"y": 70,
				"width": 240,
				"height": 56.75,
				"scaleX": 1,
				"scaleY": 1,
				"skewX": 0,
				"skewY": 0,
				"rotation": 0,
				"index": 2,
				"id": "item2",
				"image": "rank.dan_/assert/d/未命名文件夹 1/未命名文件夹 2/dsa",
				"type": 2,
				"scalingGrid": false
			},
			{
				"x": 0,
				"y": 133,
				"width": 240,
				"height": 56.75,
				"scaleX": 1,
				"scaleY": 1,
				"skewX": 0,
				"skewY": 0,
				"rotation": 0,
				"index": 3,
				"id": "item3",
				"image": "rank.dan_/assert/d/未命名文件夹 1/未命名文件夹 2/dsa",
				"type": 2,
				"scalingGrid": false
			},
			{
				"x": 0,
				"y": 198,
				"width": 240,
				"height": 56.75,
				"scaleX": 1,
				"scaleY": 1,
				"skewX": 0,
				"skewY": 0,
				"rotation": 0,
				"index": 4,
				"id": "item4",
				"image": "rank.dan_/assert/d/未命名文件夹 1/未命名文件夹 2/dsa",
				"type": 2,
				"scalingGrid": false
			},
			{
				"x": 0,
				"y": 258,
				"width": 240,
				"height": 56.75,
				"scaleX": 1,
				"scaleY": 1,
				"skewX": 0,
				"skewY": 0,
				"rotation": 0,
				"index": 5,
				"id": "item5",
				"image": "rank.dan_/assert/d/未命名文件夹 1/未命名文件夹 2/dsa",
				"type": 2,
				"scalingGrid": false
			}
		],
		"rank.dan_/assert/n.race.rank.assert/assert/c@CloseBtn": [
			{
				"x": -19,
				"y": -16,
				"width": 72.45,
				"height": 67.85,
				"scaleX": 9.056198120117188,
				"scaleY": 8.481201171875,
				"skewX": 0,
				"skewY": 0,
				"rotation": 0,
				"index": 0,
				"id": "hit_area",
				"image": "ui_commons/ui_fontsize_rect",
				"type": 0,
				"scalingGrid": false
			},
			{
				"x": 0,
				"y": 0,
				"width": 34,
				"height": 34,
				"scaleX": 1,
				"scaleY": 1,
				"skewX": 0,
				"skewY": 0,
				"rotation": 0,
				"index": 1,
				"id": "bg",
				"image": "rank.dan_/assert/n.race.rank.assert/assert/元件 9",
				"type": 0,
				"scalingGrid": false
			}
		],
		"rank.dan_/Page2": [
			{
				"x": 0,
				"y": 0,
				"width": 720,
				"height": 1280,
				"scaleX": 90,
				"scaleY": 160,
				"skewX": 0,
				"skewY": 0,
				"rotation": 0,
				"index": 0,
				"id": "hit_area",
				"image": "ui_commons/ui_fontsize_rect",
				"type": 0,
				"scalingGrid": false
			},
			{
				"x": 221,
				"y": 123,
				"width": 270,
				"height": 186,
				"scaleX": 1,
				"scaleY": 1,
				"skewX": 0,
				"skewY": 0,
				"rotation": 0,
				"index": 1,
				"id": "animalBG",
				"image": "rank.dan_/assert/as/元件 1",
				"type": 0,
				"scalingGrid": false
			},
			{
				"x": 34,
				"y": 278,
				"width": 620.75,
				"height": 731.95,
				"scaleX": 1,
				"scaleY": 1,
				"skewX": 0,
				"skewY": 0,
				"rotation": 0,
				"index": 2,
				"id": "bg",
				"image": "rank.dan_/assert/n.race.rank.assert/assert/元件 7",
				"type": 2,
				"scalingGrid": false
			},
			{
				"scaleX": 1,
				"scaleY": 1,
				"skewX": 0,
				"skewY": 0,
				"rotation": 0,
				"lineType": "single line",
				"maxCharacters": 0,
				"textType": "dynamic",
				"face": "微软雅黑",
				"size": 50,
				"fillColor": "#ffff66",
				"alignment": "center",
				"letterSpacing": 0,
				"x": 199.05,
				"y": 300.4,
				"width": 316.2,
				"height": 70,
				"index": 3,
				"id": "title",
				"type": 1
			},
			{
				"x": 78,
				"y": 767,
				"width": 566,
				"height": 223,
				"scaleX": 3.7733154296875,
				"scaleY": 1.4866180419921875,
				"skewX": 0,
				"skewY": 0,
				"rotation": 0,
				"index": 4,
				"id": "bg6",
				"image": "rank.dan_/assert/d/未命名文件夹 1/未命名文件夹 2/元件 1",
				"type": 0,
				"scalingGrid": true
			},
			{
				"x": 89,
				"y": 810,
				"width": 534.85,
				"height": 184.65,
				"scaleX": 1,
				"scaleY": 1,
				"skewX": 0,
				"skewY": 0,
				"rotation": 0,
				"index": 5,
				"id": "hbox",
				"image": "rank.dan_/assert/d/@HBox",
				"type": 2,
				"scalingGrid": false
			},
			{
				"x": 283,
				"y": 858,
				"width": 154,
				"height": 38,
				"scaleX": 1,
				"scaleY": 1,
				"skewX": 0,
				"skewY": 0,
				"rotation": 0,
				"index": 6,
				"id": "rewarded",
				"image": "rank.dan_/assert/dsa/未命名文件夹 2/元件 84",
				"type": 0,
				"scalingGrid": false
			},
			{
				"scaleX": 0.9999847412109375,
				"scaleY": 0.9999542236328125,
				"skewX": 0,
				"skewY": 0,
				"rotation": 0,
				"lineType": "single line",
				"maxCharacters": 0,
				"textType": "static",
				"face": "微软雅黑",
				"size": 26,
				"fillColor": "#663300",
				"alignment": "center",
				"letterSpacing": 0,
				"x": 83,
				"y": 777.75,
				"width": 547.95,
				"height": 38.3,
				"index": 7,
				"id": "label",
				"type": 1
			},
			{
				"x": 75,
				"y": 407,
				"width": 282,
				"height": 350.05,
				"scaleX": 1.8800048828125,
				"scaleY": 2.333740234375,
				"skewX": 0,
				"skewY": 0,
				"rotation": 0,
				"index": 8,
				"id": "bg21",
				"image": "rank.dan_/assert/n.race.rank.assert/assert/重复项目文件夹/元件 1",
				"type": 0,
				"scalingGrid": true
			},
			{
				"x": 362,
				"y": 407,
				"width": 282,
				"height": 350.05,
				"scaleX": 1.8800048828125,
				"scaleY": 2.333740234375,
				"skewX": 0,
				"skewY": 0,
				"rotation": 0,
				"index": 9,
				"id": "bg22",
				"image": "rank.dan_/assert/n.race.rank.assert/assert/重复项目文件夹/元件 1",
				"type": 0,
				"scalingGrid": true
			},
			{
				"x": 133,
				"y": 421,
				"width": 168,
				"height": 54,
				"scaleX": 1,
				"scaleY": 1,
				"skewX": 0,
				"skewY": 0,
				"rotation": 0,
				"index": 10,
				"id": "title21",
				"image": "rank.dan_/assert/n.race.rank.assert/assert/元件 5",
				"type": 0,
				"scalingGrid": false
			},
			{
				"x": 423,
				"y": 421,
				"width": 168,
				"height": 54,
				"scaleX": 1,
				"scaleY": 1,
				"skewX": 0,
				"skewY": 0,
				"rotation": 0,
				"index": 11,
				"id": "title22",
				"image": "rank.dan_/assert/n.race.rank.assert/assert/元件 83",
				"type": 0,
				"scalingGrid": false
			},
			{
				"x": 94,
				"y": 485,
				"width": 253.5,
				"height": 313.8,
				"scaleX": 1,
				"scaleY": 1,
				"skewX": 0,
				"skewY": 0,
				"rotation": 0,
				"index": 12,
				"id": "leftContent",
				"image": "rank.dan_/assert/n.race.rank.assert/left@VScroll",
				"type": 2,
				"scalingGrid": false
			},
			{
				"x": 380,
				"y": 485,
				"width": 239.3,
				"height": 246.4,
				"scaleX": 1,
				"scaleY": 1,
				"skewX": 0,
				"skewY": 0,
				"rotation": 0,
				"index": 13,
				"id": "rightContent",
				"image": "rank.dan_/assert/n.race.rank.assert/@VScroll",
				"type": 2,
				"scalingGrid": false
			},
			{
				"x": 476,
				"y": 312,
				"width": 74,
				"height": 72,
				"scaleX": 1,
				"scaleY": 1,
				"skewX": 0,
				"skewY": 0,
				"rotation": 0,
				"index": 14,
				"id": "descBtn",
				"image": "rank.dan_/assert/n.race.rank.assert/assert/desc@Button",
				"type": 2,
				"scalingGrid": false
			},
			{
				"x": 50,
				"y": 291,
				"width": 616,
				"height": 718,
				"scaleX": 5.133331298828125,
				"scaleY": 5.98333740234375,
				"skewX": 0,
				"skewY": 0,
				"rotation": 0,
				"index": 15,
				"id": "darkLayer",
				"image": "rank.dan_/assert/dsa/未命名文件夹 2/重复项目文件夹/21",
				"type": 0,
				"scalingGrid": true
			},
			{
				"x": 611,
				"y": 308,
				"width": 72.45,
				"height": 67.85,
				"scaleX": 1,
				"scaleY": 1,
				"skewX": 0,
				"skewY": 0,
				"rotation": 0,
				"index": 16,
				"id": "closeBtn",
				"image": "rank.dan_/assert/n.race.rank.assert/assert/c@CloseBtn",
				"type": 2,
				"scalingGrid": false
			},
			{
				"x": 296,
				"y": 365,
				"width": 134,
				"height": 38,
				"scaleX": 1,
				"scaleY": 1,
				"skewX": 0,
				"skewY": 0,
				"rotation": 0,
				"index": 17,
				"id": "lock",
				"image": "rank.dan_/assert/dsa/未命名文件夹 2/元件 1",
				"type": 0,
				"scalingGrid": false
			},
			{
				"x": 190,
				"y": 270,
				"width": 339.7,
				"height": 61.25,
				"scaleX": 1,
				"scaleY": 1,
				"skewX": 0,
				"skewY": 0,
				"rotation": 0,
				"index": 18,
				"id": "animalFG",
				"image": "rank.dan_/assert/as/元件 4",
				"type": 2,
				"scalingGrid": false
			}
		],
		"rank.dan_/Page1": [
			{
				"x": 0,
				"y": 0,
				"width": 720,
				"height": 1280,
				"scaleX": 90,
				"scaleY": 160,
				"skewX": 0,
				"skewY": 0,
				"rotation": 0,
				"index": 0,
				"id": "hit_area",
				"image": "ui_commons/ui_fontsize_rect",
				"type": 0,
				"scalingGrid": false
			},
			{
				"x": 219,
				"y": 122,
				"width": 301,
				"height": 184,
				"scaleX": 1,
				"scaleY": 1,
				"skewX": 0,
				"skewY": 0,
				"rotation": 0,
				"index": 1,
				"id": "animalBG",
				"image": "rank.dan_/asw/元件 2",
				"type": 0,
				"scalingGrid": false
			},
			{
				"x": 34,
				"y": 278,
				"width": 620.75,
				"height": 731.95,
				"scaleX": 1,
				"scaleY": 1,
				"skewX": 0,
				"skewY": 0,
				"rotation": 0,
				"index": 2,
				"id": "bg",
				"image": "rank.dan_/assert/n.race.rank.assert/assert/元件 7",
				"type": 2,
				"scalingGrid": false
			},
			{
				"x": 476,
				"y": 312,
				"width": 74,
				"height": 72,
				"scaleX": 1,
				"scaleY": 1,
				"skewX": 0,
				"skewY": 0,
				"rotation": 0,
				"index": 3,
				"id": "descBtn",
				"image": "rank.dan_/assert/n.race.rank.assert/assert/desc@Button",
				"type": 2,
				"scalingGrid": false
			},
			{
				"scaleX": 1,
				"scaleY": 1,
				"skewX": 0,
				"skewY": 0,
				"rotation": 0,
				"lineType": "single line",
				"maxCharacters": 0,
				"textType": "dynamic",
				"face": "微软雅黑",
				"size": 50,
				"fillColor": "#ffff66",
				"alignment": "center",
				"letterSpacing": 0,
				"x": 199.05,
				"y": 300.4,
				"width": 316.2,
				"height": 70,
				"index": 4,
				"id": "title",
				"type": 1
			},
			{
				"x": 78,
				"y": 767,
				"width": 566,
				"height": 223,
				"scaleX": 3.7733154296875,
				"scaleY": 1.4866180419921875,
				"skewX": 0,
				"skewY": 0,
				"rotation": 0,
				"index": 5,
				"id": "bg6",
				"image": "rank.dan_/assert/d/未命名文件夹 1/未命名文件夹 2/元件 1",
				"type": 0,
				"scalingGrid": true
			},
			{
				"x": 89,
				"y": 810,
				"width": 534.85,
				"height": 184.65,
				"scaleX": 1,
				"scaleY": 1,
				"skewX": 0,
				"skewY": 0,
				"rotation": 0,
				"index": 6,
				"id": "hbox",
				"image": "rank.dan_/assert/d/@HBox",
				"type": 2,
				"scalingGrid": false
			},
			{
				"x": 283,
				"y": 858,
				"width": 154,
				"height": 38,
				"scaleX": 1,
				"scaleY": 1,
				"skewX": 0,
				"skewY": 0,
				"rotation": 0,
				"index": 7,
				"id": "rewarded",
				"image": "rank.dan_/assert/dsa/未命名文件夹 2/元件 84",
				"type": 0,
				"scalingGrid": false
			},
			{
				"scaleX": 0.9999847412109375,
				"scaleY": 0.9999542236328125,
				"skewX": 0,
				"skewY": 0,
				"rotation": 0,
				"lineType": "single line",
				"maxCharacters": 0,
				"textType": "static",
				"face": "微软雅黑",
				"size": 26,
				"fillColor": "#663300",
				"alignment": "center",
				"letterSpacing": 0,
				"x": 83,
				"y": 777.75,
				"width": 547.95,
				"height": 38.3,
				"index": 8,
				"id": "label",
				"type": 1
			},
			{
				"x": 75,
				"y": 407,
				"width": 282,
				"height": 350.05,
				"scaleX": 1.8800048828125,
				"scaleY": 2.333740234375,
				"skewX": 0,
				"skewY": 0,
				"rotation": 0,
				"index": 9,
				"id": "bg21",
				"image": "rank.dan_/assert/n.race.rank.assert/assert/重复项目文件夹/元件 1",
				"type": 0,
				"scalingGrid": true
			},
			{
				"x": 362,
				"y": 407,
				"width": 282,
				"height": 350.05,
				"scaleX": 1.8800048828125,
				"scaleY": 2.333740234375,
				"skewX": 0,
				"skewY": 0,
				"rotation": 0,
				"index": 10,
				"id": "bg22",
				"image": "rank.dan_/assert/n.race.rank.assert/assert/重复项目文件夹/元件 1",
				"type": 0,
				"scalingGrid": true
			},
			{
				"x": 133,
				"y": 421,
				"width": 168,
				"height": 54,
				"scaleX": 1,
				"scaleY": 1,
				"skewX": 0,
				"skewY": 0,
				"rotation": 0,
				"index": 11,
				"id": "title21",
				"image": "rank.dan_/assert/n.race.rank.assert/assert/元件 5",
				"type": 0,
				"scalingGrid": false
			},
			{
				"x": 423,
				"y": 421,
				"width": 168,
				"height": 54,
				"scaleX": 1,
				"scaleY": 1,
				"skewX": 0,
				"skewY": 0,
				"rotation": 0,
				"index": 12,
				"id": "title22",
				"image": "rank.dan_/assert/n.race.rank.assert/assert/元件 83",
				"type": 0,
				"scalingGrid": false
			},
			{
				"x": 94,
				"y": 485,
				"width": 253.5,
				"height": 313.8,
				"scaleX": 1,
				"scaleY": 1,
				"skewX": 0,
				"skewY": 0,
				"rotation": 0,
				"index": 13,
				"id": "leftContent",
				"image": "rank.dan_/assert/n.race.rank.assert/left@VScroll",
				"type": 2,
				"scalingGrid": false
			},
			{
				"x": 380,
				"y": 485,
				"width": 239.3,
				"height": 246.4,
				"scaleX": 1,
				"scaleY": 1,
				"skewX": 0,
				"skewY": 0,
				"rotation": 0,
				"index": 14,
				"id": "rightContent",
				"image": "rank.dan_/assert/n.race.rank.assert/@VScroll",
				"type": 2,
				"scalingGrid": false
			},
			{
				"x": 50,
				"y": 291,
				"width": 616,
				"height": 718,
				"scaleX": 5.133331298828125,
				"scaleY": 5.98333740234375,
				"skewX": 0,
				"skewY": 0,
				"rotation": 0,
				"index": 15,
				"id": "darkLayer",
				"image": "rank.dan_/assert/dsa/未命名文件夹 2/重复项目文件夹/21",
				"type": 0,
				"scalingGrid": true
			},
			{
				"x": 611,
				"y": 308,
				"width": 72.45,
				"height": 67.85,
				"scaleX": 1,
				"scaleY": 1,
				"skewX": 0,
				"skewY": 0,
				"rotation": 0,
				"index": 16,
				"id": "closeBtn",
				"image": "rank.dan_/assert/n.race.rank.assert/assert/c@CloseBtn",
				"type": 2,
				"scalingGrid": false
			},
			{
				"x": 296,
				"y": 365,
				"width": 134,
				"height": 38,
				"scaleX": 1,
				"scaleY": 1,
				"skewX": 0,
				"skewY": 0,
				"rotation": 0,
				"index": 17,
				"id": "lock",
				"image": "rank.dan_/assert/dsa/未命名文件夹 2/元件 1",
				"type": 0,
				"scalingGrid": false
			},
			{
				"x": 202,
				"y": 270,
				"width": 339.7,
				"height": 61.25,
				"scaleX": 1,
				"scaleY": 1,
				"skewX": 0,
				"skewY": 0,
				"rotation": 0,
				"index": 18,
				"id": "animalFG",
				"image": "rank.dan_/asw/元件 86",
				"type": 2,
				"scalingGrid": false
			}
		],
		"rank.dan_/asw/元件 86": [
			{
				"x": 272,
				"y": 0,
				"width": 68,
				"height": 61,
				"scaleX": 1,
				"scaleY": 1,
				"skewX": 0,
				"skewY": 0,
				"rotation": 0,
				"index": 0,
				"id": "元件 84",
				"image": "rank.dan_/asw/元件 84",
				"type": 0,
				"scalingGrid": false
			},
			{
				"x": 0,
				"y": 0,
				"width": 68,
				"height": 61,
				"scaleX": 1,
				"scaleY": 1,
				"skewX": 0,
				"skewY": 0,
				"rotation": 0,
				"index": 1,
				"id": "元件 85",
				"image": "rank.dan_/asw/元件 85",
				"type": 0,
				"scalingGrid": false
			}
		],
		"rank.dan_/Page10": [
			{
				"x": 0,
				"y": 0,
				"width": 720,
				"height": 1280,
				"scaleX": 90,
				"scaleY": 160,
				"skewX": 0,
				"skewY": 0,
				"rotation": 0,
				"index": 0,
				"id": "hit_area",
				"image": "ui_commons/ui_fontsize_rect",
				"type": 0,
				"scalingGrid": false
			},
			{
				"x": 193,
				"y": 120,
				"width": 341,
				"height": 195,
				"scaleX": 1,
				"scaleY": 1,
				"skewX": 0,
				"skewY": 0,
				"rotation": 0,
				"index": 1,
				"id": "animalBG1",
				"image": "rank.dan_/assert/n.race.rank.assert/assert/元件 6",
				"type": 0,
				"scalingGrid": false
			},
			{
				"x": 34,
				"y": 278,
				"width": 620.75,
				"height": 731.95,
				"scaleX": 1,
				"scaleY": 1,
				"skewX": 0,
				"skewY": 0,
				"rotation": 0,
				"index": 2,
				"id": "bg",
				"image": "rank.dan_/assert/n.race.rank.assert/assert/元件 7",
				"type": 2,
				"scalingGrid": false
			},
			{
				"x": 476,
				"y": 312,
				"width": 74,
				"height": 72,
				"scaleX": 1,
				"scaleY": 1,
				"skewX": 0,
				"skewY": 0,
				"rotation": 0,
				"index": 3,
				"id": "descBtn",
				"image": "rank.dan_/assert/n.race.rank.assert/assert/desc@Button",
				"type": 2,
				"scalingGrid": false
			},
			{
				"scaleX": 1,
				"scaleY": 1,
				"skewX": 0,
				"skewY": 0,
				"rotation": 0,
				"lineType": "single line",
				"maxCharacters": 0,
				"textType": "dynamic",
				"face": "微软雅黑",
				"size": 50,
				"fillColor": "#ffff66",
				"alignment": "center",
				"letterSpacing": 0,
				"x": 199.05,
				"y": 300.4,
				"width": 316.2,
				"height": 70,
				"index": 4,
				"id": "title",
				"type": 1
			},
			{
				"x": 75,
				"y": 768,
				"width": 566,
				"height": 223,
				"scaleX": 3.7733154296875,
				"scaleY": 1.4866180419921875,
				"skewX": 0,
				"skewY": 0,
				"rotation": 0,
				"index": 5,
				"id": "bg6",
				"image": "rank.dan_/assert/d/未命名文件夹 1/未命名文件夹 2/元件 1",
				"type": 0,
				"scalingGrid": true
			},
			{
				"x": 489,
				"y": 885,
				"width": 229.5,
				"height": 102.85,
				"scaleX": 0.8499908447265625,
				"scaleY": 0.8499908447265625,
				"skewX": 0,
				"skewY": 0,
				"rotation": 0,
				"index": 6,
				"id": "button2",
				"image": "ui_buttons_new/btn_text",
				"type": 2,
				"scalingGrid": false
			},
			{
				"x": 224,
				"y": 885,
				"width": 229.5,
				"height": 102.85,
				"scaleX": 0.8499908447265625,
				"scaleY": 0.8499908447265625,
				"skewX": 0,
				"skewY": 0,
				"rotation": 0,
				"index": 7,
				"id": "button1",
				"image": "ui_buttons_new/btn_text",
				"type": 2,
				"scalingGrid": false
			},
			{
				"x": 75,
				"y": 407,
				"width": 282,
				"height": 350.05,
				"scaleX": 1.8800048828125,
				"scaleY": 2.333740234375,
				"skewX": 0,
				"skewY": 0,
				"rotation": 0,
				"index": 8,
				"id": "bg21",
				"image": "rank.dan_/assert/n.race.rank.assert/assert/重复项目文件夹/元件 1",
				"type": 0,
				"scalingGrid": true
			},
			{
				"x": 362,
				"y": 407,
				"width": 282,
				"height": 350.05,
				"scaleX": 1.8800048828125,
				"scaleY": 2.333740234375,
				"skewX": 0,
				"skewY": 0,
				"rotation": 0,
				"index": 9,
				"id": "bg22",
				"image": "rank.dan_/assert/n.race.rank.assert/assert/重复项目文件夹/元件 1",
				"type": 0,
				"scalingGrid": true
			},
			{
				"x": 94,
				"y": 485,
				"width": 253.5,
				"height": 313.8,
				"scaleX": 1,
				"scaleY": 1,
				"skewX": 0,
				"skewY": 0,
				"rotation": 0,
				"index": 10,
				"id": "leftContent",
				"image": "rank.dan_/assert/n.race.rank.assert/left@VScroll",
				"type": 2,
				"scalingGrid": false
			},
			{
				"x": 380,
				"y": 485,
				"width": 239.3,
				"height": 246.4,
				"scaleX": 1,
				"scaleY": 1,
				"skewX": 0,
				"skewY": 0,
				"rotation": 0,
				"index": 11,
				"id": "rightContent",
				"image": "rank.dan_/assert/n.race.rank.assert/@VScroll",
				"type": 2,
				"scalingGrid": false
			},
			{
				"x": 133,
				"y": 421,
				"width": 168,
				"height": 54,
				"scaleX": 1,
				"scaleY": 1,
				"skewX": 0,
				"skewY": 0,
				"rotation": 0,
				"index": 12,
				"id": "title21",
				"image": "rank.dan_/assert/n.race.rank.assert/assert/元件 5",
				"type": 0,
				"scalingGrid": false
			},
			{
				"x": 423,
				"y": 421,
				"width": 168,
				"height": 54,
				"scaleX": 1,
				"scaleY": 1,
				"skewX": 0,
				"skewY": 0,
				"rotation": 0,
				"index": 13,
				"id": "title22",
				"image": "rank.dan_/assert/n.race.rank.assert/assert/元件 83",
				"type": 0,
				"scalingGrid": false
			},
			{
				"x": 136,
				"y": 790,
				"width": 425,
				"height": 38,
				"scaleX": 1,
				"scaleY": 1,
				"skewX": 0,
				"skewY": 0,
				"rotation": 0,
				"index": 14,
				"id": "bottomText3",
				"image": "bottomText3",
				"type": 0,
				"scalingGrid": false
			},
			{
				"x": 150,
				"y": 789,
				"width": 403,
				"height": 38,
				"scaleX": 1,
				"scaleY": 1,
				"skewX": 0,
				"skewY": 0,
				"rotation": 0,
				"index": 15,
				"id": "bottomText2",
				"image": "bottomText2",
				"type": 0,
				"scalingGrid": false
			},
			{
				"x": 186,
				"y": 938,
				"width": 351,
				"height": 37,
				"scaleX": 1,
				"scaleY": 1,
				"skewX": 0,
				"skewY": 0,
				"rotation": 0,
				"index": 16,
				"id": "bottomText1",
				"image": "bottomText1",
				"type": 0,
				"scalingGrid": false
			},
			{
				"x": 575,
				"y": 781,
				"width": 51,
				"height": 56,
				"scaleX": 1,
				"scaleY": 1,
				"skewX": 0,
				"skewY": 0,
				"rotation": 0,
				"index": 17,
				"id": "newHead",
				"image": "rank.dan_/newheadctrl",
				"type": 2,
				"scalingGrid": false
			},
			{
				"x": 601,
				"y": 791,
				"width": 553,
				"height": 331,
				"scaleX": 1,
				"scaleY": 1,
				"skewX": 0,
				"skewY": 0,
				"rotation": 0,
				"index": 18,
				"id": "newHeadIntroduce",
				"image": "rank.dan_/headTipUI",
				"type": 2,
				"scalingGrid": false
			},
			{
				"scaleX": 0.9999847412109375,
				"scaleY": 0.9999542236328125,
				"skewX": 0,
				"skewY": 0,
				"rotation": 0,
				"lineType": "single line",
				"maxCharacters": 0,
				"textType": "dynamic",
				"face": "微软雅黑",
				"size": 24,
				"fillColor": "#cc0000",
				"alignment": "center",
				"letterSpacing": 0,
				"x": 283.4,
				"y": 939.05,
				"width": 96.6,
				"height": 35.7,
				"index": 19,
				"id": "friendNum",
				"type": 1
			},
			{
				"x": 265,
				"y": 779,
				"width": 57,
				"height": 63,
				"scaleX": 1,
				"scaleY": 1,
				"skewX": 0,
				"skewY": 0,
				"rotation": 0,
				"index": 20,
				"id": "stone",
				"image": "rank.dan_/assert/n.race.rank.assert/assert/元件 11",
				"type": 0,
				"scalingGrid": false
			},
			{
				"scaleX": 0.9999847412109375,
				"scaleY": 0.9999542236328125,
				"skewX": 0,
				"skewY": 0,
				"rotation": 0,
				"lineType": "single line",
				"maxCharacters": 0,
				"textType": "dynamic",
				"face": "微软雅黑",
				"size": 26,
				"fillColor": "#663300",
				"alignment": "center",
				"letterSpacing": 0,
				"x": 312.45,
				"y": 789.6,
				"width": 68.05,
				"height": 38.3,
				"index": 21,
				"id": "stoneNum",
				"type": 1
			},
			{
				"x": 50,
				"y": 290,
				"width": 616,
				"height": 718,
				"scaleX": 5.133331298828125,
				"scaleY": 5.98333740234375,
				"skewX": 0,
				"skewY": 0,
				"rotation": 0,
				"index": 22,
				"id": "darkLayer",
				"image": "rank.dan_/assert/dsa/未命名文件夹 2/重复项目文件夹/21",
				"type": 0,
				"scalingGrid": true
			},
			{
				"x": 611,
				"y": 308,
				"width": 72.45,
				"height": 67.85,
				"scaleX": 1,
				"scaleY": 1,
				"skewX": 0,
				"skewY": 0,
				"rotation": 0,
				"index": 23,
				"id": "closeBtn",
				"image": "rank.dan_/assert/n.race.rank.assert/assert/c@CloseBtn",
				"type": 2,
				"scalingGrid": false
			},
			{
				"x": 296,
				"y": 365,
				"width": 134,
				"height": 38,
				"scaleX": 1,
				"scaleY": 1,
				"skewX": 0,
				"skewY": 0,
				"rotation": 0,
				"index": 24,
				"id": "lock",
				"image": "rank.dan_/assert/dsa/未命名文件夹 2/元件 1",
				"type": 0,
				"scalingGrid": false
			},
			{
				"x": 202,
				"y": 253,
				"width": 361.55,
				"height": 67.05,
				"scaleX": 1,
				"scaleY": 1,
				"skewX": 0,
				"skewY": 0,
				"rotation": 0,
				"index": 25,
				"id": "animalFG",
				"image": "rank.dan_/assert/n.race.rank.assert/assert/重复项目文件夹/元件 7",
				"type": 2,
				"scalingGrid": false
			}
		],
		"ui_buttons_new/btn_text": [
			{
				"x": -135,
				"y": -60,
				"width": 270,
				"height": 120,
				"scaleX": 9,
				"scaleY": 4,
				"skewX": 0,
				"skewY": 0,
				"rotation": 0,
				"index": 0,
				"id": "hit_area",
				"image": "ui_commons/ui_transparent_rect",
				"type": 0,
				"scalingGrid": false
			},
			{
				"x": -132,
				"y": -17,
				"width": 264,
				"height": 78,
				"scaleX": 1,
				"scaleY": 1,
				"skewX": 0,
				"skewY": 0,
				"rotation": 0,
				"index": 1,
				"id": "_shadow",
				"image": "ui_buttons_new/btn_shadow",
				"type": 0,
				"scalingGrid": true
			},
			{
				"x": -135,
				"y": -54,
				"width": 270,
				"height": 108,
				"scaleX": 1,
				"scaleY": 1,
				"skewX": 0,
				"skewY": 0,
				"rotation": 0,
				"index": 2,
				"id": "background",
				"image": "ui_buttons_new/btn_bg",
				"type": 0,
				"scalingGrid": true
			},
			{
				"x": -115,
				"y": -32,
				"width": 230,
				"height": 64,
				"scaleX": 28.74981689453125,
				"scaleY": 8.000091552734375,
				"skewX": 0,
				"skewY": 0,
				"rotation": 0,
				"index": 3,
				"id": "labelSize",
				"image": "ui_commons/ui_fontsize_rect",
				"type": 0,
				"scalingGrid": false
			},
			{
				"scaleX": 1,
				"scaleY": 1,
				"skewX": 0,
				"skewY": 0,
				"rotation": 0,
				"lineType": "single line",
				"maxCharacters": 0,
				"textType": "dynamic",
				"face": "微软雅黑",
				"size": 44,
				"fillColor": "#ffffff",
				"alignment": "center",
				"letterSpacing": 0,
				"x": -112.25,
				"y": -35,
				"width": 224.5,
				"height": 62.05,
				"index": 4,
				"id": "label",
				"type": 1
			}
		],
		"rank.dan_/newheadctrl": [
			{
				"x": 0,
				"y": 0,
				"width": 51,
				"height": 56,
				"scaleX": 1,
				"scaleY": 1,
				"skewX": 0,
				"skewY": 0,
				"rotation": 0,
				"index": 0,
				"id": "图层 1",
				"image": "rank.dan_/newhead",
				"type": 0,
				"scalingGrid": false
			}
		],
		"rank.dan_/headTipUI": [
			{
				"x": -495,
				"y": -320,
				"width": 553,
				"height": 331,
				"scaleX": 1,
				"scaleY": 1,
				"skewX": 0,
				"skewY": 0,
				"rotation": 0,
				"index": 0,
				"id": "bg",
				"image": "rank.dan_/headtipctrl",
				"type": 0,
				"scalingGrid": false
			}
		],
		"rank.dan_/assert/n.race.rank.assert/assert/重复项目文件夹/元件 7": [
			{
				"x": -24,
				"y": 14,
				"width": 361.55,
				"height": 67.05,
				"scaleX": 1,
				"scaleY": 1,
				"skewX": 0,
				"skewY": 0,
				"rotation": 0,
				"index": 0,
				"id": "2",
				"image": "rank.dan_/assert/as/元件 86",
				"type": 2,
				"scalingGrid": false
			}
		],
		"rank.dan_/assert/n.race.rank.assert/assert/4th.set.niu/未命名文件夹 2/wmy.2018/ui_buttons/ui_button_label": [
			{
				"x": -121,
				"y": -43,
				"width": 259.7,
				"height": 94,
				"scaleX": 32.45976257324219,
				"scaleY": 11.749771118164062,
				"skewX": 0,
				"skewY": 0,
				"rotation": 0,
				"alphaPercent": 0,
				"index": 0,
				"id": "hit_area",
				"image": "ui_commons/ui_fontsize_rect",
				"type": 0,
				"scalingGrid": false
			},
			{
				"x": -153,
				"y": -29,
				"width": 322.05,
				"height": 107,
				"scaleX": 1.1259765625,
				"scaleY": 0.86297607421875,
				"skewX": 0,
				"skewY": 0,
				"rotation": 0,
				"index": 1,
				"id": "_shadow",
				"image": "rank.dan_/assert/n.race.rank.assert/assert/4th.set.niu/未命名文件夹 2/wmy.2018/ui_buttons/button_common/ui_button_shadow",
				"type": 0,
				"scalingGrid": false
			},
			{
				"x": -155,
				"y": -63,
				"width": 328.35,
				"height": 133.95,
				"scaleX": 1.2438201904296875,
				"scaleY": 1.0465087890625,
				"skewX": 0,
				"skewY": 0,
				"rotation": 0,
				"index": 2,
				"id": "background",
				"image": "rank.dan_/assert/n.race.rank.assert/assert/4th.set.niu/未命名文件夹 2/wmy.2018/123/重复项目文件夹/ui_button_green_scale9",
				"type": 0,
				"scalingGrid": true
			},
			{
				"x": -130,
				"y": -28,
				"width": 269.6,
				"height": 67.55,
				"scaleX": 33.70158386230469,
				"scaleY": 8.4464111328125,
				"skewX": 0,
				"skewY": 0,
				"rotation": 0,
				"index": 3,
				"id": "labelSize",
				"image": "ui_commons/ui_fontsize_rect",
				"type": 0,
				"scalingGrid": false
			},
			{
				"scaleX": 1,
				"scaleY": 1,
				"skewX": 0,
				"skewY": 0,
				"rotation": 0,
				"lineType": "single line",
				"maxCharacters": 0,
				"textType": "dynamic",
				"face": "微软雅黑",
				"size": 40,
				"fillColor": "#ffffff",
				"alignment": "center",
				"letterSpacing": 0,
				"x": -98.95,
				"y": -29.1,
				"width": 206.05,
				"height": 56.75,
				"index": 4,
				"id": "label",
				"type": 1
			}
		],
		"rank.dan_/assert/n.race.rank.assert/assert/元件 3": [
			{
				"x": 0,
				"y": 0,
				"width": 23,
				"height": 23,
				"scaleX": 1,
				"scaleY": 1,
				"skewX": 0,
				"skewY": 0,
				"rotation": 0,
				"index": 0,
				"id": "2",
				"image": "rank.dan_/assert/n.race.rank.assert/assert/元件 1",
				"type": 0,
				"scalingGrid": false
			},
			{
				"x": 3,
				"y": 3,
				"width": 17,
				"height": 17,
				"scaleX": 1,
				"scaleY": 1,
				"skewX": 0,
				"skewY": 0,
				"rotation": 0,
				"index": 1,
				"id": "1",
				"image": "rank.dan_/assert/n.race.rank.assert/assert/元件 2",
				"type": 0,
				"scalingGrid": false
			}
		],
		"rank.dan_/assert/n.race.rank.assert/assert/元件 4": [
			{
				"x": 284,
				"y": 0,
				"width": 23,
				"height": 23,
				"scaleX": 1,
				"scaleY": 1,
				"skewX": 0,
				"skewY": 0,
				"rotation": 0,
				"index": 0,
				"id": "10",
				"image": "rank.dan_/assert/n.race.rank.assert/assert/元件 3",
				"type": 2,
				"scalingGrid": false
			},
			{
				"x": 221,
				"y": 0,
				"width": 23,
				"height": 23,
				"scaleX": 1,
				"scaleY": 1,
				"skewX": 0,
				"skewY": 0,
				"rotation": 0,
				"index": 1,
				"id": "8",
				"image": "rank.dan_/assert/n.race.rank.assert/assert/元件 3",
				"type": 2,
				"scalingGrid": false
			},
			{
				"x": 158,
				"y": 0,
				"width": 23,
				"height": 23,
				"scaleX": 1,
				"scaleY": 1,
				"skewX": 0,
				"skewY": 0,
				"rotation": 0,
				"index": 2,
				"id": "6",
				"image": "rank.dan_/assert/n.race.rank.assert/assert/元件 3",
				"type": 2,
				"scalingGrid": false
			},
			{
				"x": 189,
				"y": 0,
				"width": 23,
				"height": 23,
				"scaleX": 1,
				"scaleY": 1,
				"skewX": 0,
				"skewY": 0,
				"rotation": 0,
				"index": 3,
				"id": "7",
				"image": "rank.dan_/assert/n.race.rank.assert/assert/元件 3",
				"type": 2,
				"scalingGrid": false
			},
			{
				"x": 0,
				"y": 0,
				"width": 23,
				"height": 23,
				"scaleX": 1,
				"scaleY": 1,
				"skewX": 0,
				"skewY": 0,
				"rotation": 0,
				"index": 4,
				"id": "1",
				"image": "rank.dan_/assert/n.race.rank.assert/assert/元件 3",
				"type": 2,
				"scalingGrid": false
			},
			{
				"x": 126,
				"y": 0,
				"width": 23,
				"height": 23,
				"scaleX": 1,
				"scaleY": 1,
				"skewX": 0,
				"skewY": 0,
				"rotation": 0,
				"index": 5,
				"id": "5",
				"image": "rank.dan_/assert/n.race.rank.assert/assert/元件 3",
				"type": 2,
				"scalingGrid": false
			},
			{
				"x": 95,
				"y": 0,
				"width": 23,
				"height": 23,
				"scaleX": 1,
				"scaleY": 1,
				"skewX": 0,
				"skewY": 0,
				"rotation": 0,
				"index": 6,
				"id": "4",
				"image": "rank.dan_/assert/n.race.rank.assert/assert/元件 3",
				"type": 2,
				"scalingGrid": false
			},
			{
				"x": 63,
				"y": 0,
				"width": 23,
				"height": 23,
				"scaleX": 1,
				"scaleY": 1,
				"skewX": 0,
				"skewY": 0,
				"rotation": 0,
				"index": 7,
				"id": "3",
				"image": "rank.dan_/assert/n.race.rank.assert/assert/元件 3",
				"type": 2,
				"scalingGrid": false
			},
			{
				"x": 32,
				"y": 0,
				"width": 23,
				"height": 23,
				"scaleX": 1,
				"scaleY": 1,
				"skewX": 0,
				"skewY": 0,
				"rotation": 0,
				"index": 8,
				"id": "2",
				"image": "rank.dan_/assert/n.race.rank.assert/assert/元件 3",
				"type": 2,
				"scalingGrid": false
			},
			{
				"x": 252,
				"y": 0,
				"width": 23,
				"height": 23,
				"scaleX": 1,
				"scaleY": 1,
				"skewX": 0,
				"skewY": 0,
				"rotation": 0,
				"index": 9,
				"id": "9",
				"image": "rank.dan_/assert/n.race.rank.assert/assert/元件 3",
				"type": 2,
				"scalingGrid": false
			}
		],
		"rank.dan_/historyUI": [
			{
				"x": 0,
				"y": 0,
				"width": 124,
				"height": 44,
				"scaleX": 1,
				"scaleY": 1,
				"skewX": 0,
				"skewY": 0,
				"rotation": 0,
				"index": 0,
				"id": "图层 1",
				"image": "rank.dan_/history",
				"type": 0,
				"scalingGrid": false
			}
		],
		"rank.dan_/rank.dan": [
			{
				"x": 0,
				"y": 0,
				"width": 720,
				"height": 1280,
				"scaleX": 90,
				"scaleY": 160,
				"skewX": 0,
				"skewY": 0,
				"rotation": 0,
				"index": 0,
				"id": "hit_area",
				"image": "ui_commons/ui_fontsize_rect",
				"type": 0,
				"scalingGrid": false
			},
			{
				"x": 0,
				"y": 0,
				"width": 720,
				"height": 1280,
				"scaleX": 1,
				"scaleY": 1,
				"skewX": 0,
				"skewY": 0,
				"rotation": 0,
				"index": 1,
				"id": "pageView",
				"image": "rank.dan_/assert/n.race.rank.assert/assert/4th.set.niu/noClip@Page",
				"type": 2,
				"scalingGrid": false
			},
			{
				"x": 218,
				"y": 1039,
				"width": 306.65,
				"height": 23,
				"scaleX": 1,
				"scaleY": 1,
				"skewX": 0,
				"skewY": 0,
				"rotation": 0,
				"index": 2,
				"id": "bar",
				"image": "rank.dan_/assert/n.race.rank.assert/assert/元件 4",
				"type": 2,
				"scalingGrid": false
			},
			{
				"x": 540,
				"y": 1027,
				"width": 124,
				"height": 44,
				"scaleX": 1,
				"scaleY": 1,
				"skewX": 0,
				"skewY": 0,
				"rotation": 0,
				"index": 3,
				"id": "history",
				"image": "rank.dan_/historyUI",
				"type": 2,
				"scalingGrid": false
			}
		],
		"rank.dan_/skillInfo": [
			{
				"scaleX": 1,
				"scaleY": 1,
				"skewX": 0,
				"skewY": 0,
				"rotation": 0,
				"lineType": "single line",
				"maxCharacters": 0,
				"textType": "static",
				"face": "微软雅黑",
				"size": 22,
				"fillColor": "#663300",
				"alignment": "left",
				"letterSpacing": 0,
				"x": 74,
				"y": 4,
				"width": 160,
				"height": 62.1,
				"index": 0,
				"id": "label",
				"type": 1
			},
			{
				"x": 0,
				"y": 0,
				"width": 70,
				"height": 70,
				"scaleX": 8.75,
				"scaleY": 8.75,
				"skewX": 0,
				"skewY": 0,
				"rotation": 0,
				"index": 1,
				"id": "icon",
				"image": "ui_commons/ui_fontsize_rect",
				"type": 0,
				"scalingGrid": false
			}
		],
		"rank.dan_/skillInfoPic": [
			{
				"x": 0,
				"y": 0,
				"width": 60,
				"height": 54,
				"scaleX": 1,
				"scaleY": 1,
				"skewX": 0,
				"skewY": 0,
				"rotation": 0,
				"index": 0,
				"id": "1",
				"image": "rank.dan_/skill_1",
				"type": 0,
				"scalingGrid": false
			},
			{
				"x": 63,
				"y": 0,
				"width": 60,
				"height": 54,
				"scaleX": 1,
				"scaleY": 1,
				"skewX": 0,
				"skewY": 0,
				"rotation": 0,
				"index": 1,
				"id": "2",
				"image": "rank.dan_/skill_3",
				"type": 0,
				"scalingGrid": false
			},
			{
				"x": 258,
				"y": 0,
				"width": 60,
				"height": 54,
				"scaleX": 1,
				"scaleY": 1,
				"skewX": 0,
				"skewY": 0,
				"rotation": 0,
				"index": 2,
				"id": "3",
				"image": "rank.dan_/skill_5",
				"type": 0,
				"scalingGrid": false
			},
			{
				"x": 128,
				"y": 0,
				"width": 60,
				"height": 54,
				"scaleX": 1,
				"scaleY": 1,
				"skewX": 0,
				"skewY": 0,
				"rotation": 0,
				"index": 3,
				"id": "4",
				"image": "rank.dan_/skill_4",
				"type": 0,
				"scalingGrid": false
			},
			{
				"x": 185,
				"y": 0,
				"width": 60,
				"height": 54,
				"scaleX": 1,
				"scaleY": 1,
				"skewX": 0,
				"skewY": 0,
				"rotation": 0,
				"index": 4,
				"id": "5",
				"image": "rank.dan_/skill_2",
				"type": 0,
				"scalingGrid": false
			}
		],
		"ui_buttons_new/btn_icon_num_text": [
			{
				"x": -135,
				"y": -60,
				"width": 270,
				"height": 120,
				"scaleX": 9,
				"scaleY": 4,
				"skewX": 0,
				"skewY": 0,
				"rotation": 0,
				"index": 0,
				"id": "hit_area",
				"image": "ui_commons/ui_transparent_rect",
				"type": 0,
				"scalingGrid": false
			},
			{
				"x": -132,
				"y": -17,
				"width": 264,
				"height": 78,
				"scaleX": 1,
				"scaleY": 1,
				"skewX": 0,
				"skewY": 0,
				"rotation": 0,
				"index": 1,
				"id": "_shadow",
				"image": "ui_buttons_new/btn_shadow",
				"type": 0,
				"scalingGrid": true
			},
			{
				"x": -135,
				"y": -54,
				"width": 270,
				"height": 108,
				"scaleX": 1,
				"scaleY": 1,
				"skewX": 0,
				"skewY": 0,
				"rotation": 0,
				"index": 2,
				"id": "background",
				"image": "ui_buttons_new/btn_bg",
				"type": 0,
				"scalingGrid": true
			},
			{
				"x": 6,
				"y": -32,
				"width": 96.05,
				"height": 64,
				"scaleX": 12.00799560546875,
				"scaleY": 8.000091552734375,
				"skewX": 0,
				"skewY": 0,
				"rotation": 0,
				"index": 3,
				"id": "labelSize",
				"image": "ui_commons/ui_fontsize_rect",
				"type": 0,
				"scalingGrid": false
			},
			{
				"scaleX": 1,
				"scaleY": 1,
				"skewX": 0,
				"skewY": 0,
				"rotation": 0,
				"lineType": "single line",
				"maxCharacters": 0,
				"textType": "dynamic",
				"face": "微软雅黑",
				"size": 44,
				"fillColor": "#ffffff",
				"alignment": "left",
				"letterSpacing": 0,
				"x": 6.75,
				"y": -31.05,
				"width": 95.25,
				"height": 62.05,
				"index": 4,
				"id": "label",
				"type": 1
			},
			{
				"x": -39,
				"y": -32,
				"width": 33,
				"height": 64,
				"scaleX": 4.12774658203125,
				"scaleY": 8.000091552734375,
				"skewX": 0,
				"skewY": 0,
				"rotation": 0,
				"index": 5,
				"id": "numberSize",
				"image": "ui_commons/ui_fontsize_rect",
				"type": 0,
				"scalingGrid": false
			},
			{
				"scaleX": 1,
				"scaleY": 1,
				"skewX": 0,
				"skewY": 0,
				"rotation": 0,
				"lineType": "single line",
				"maxCharacters": 0,
				"textType": "dynamic",
				"face": "微软雅黑",
				"size": 44,
				"fillColor": "#ffffff",
				"alignment": "left",
				"letterSpacing": 0,
				"x": -39.25,
				"y": -31.05,
				"width": 33.25,
				"height": 62.05,
				"index": 6,
				"id": "number",
				"type": 1
			},
			{
				"x": -103,
				"y": -35,
				"width": 58,
				"height": 70,
				"scaleX": 7.248291015625,
				"scaleY": 8.749801635742188,
				"skewX": 0,
				"skewY": 0,
				"rotation": 0,
				"index": 7,
				"id": "iconSize",
				"image": "ui_commons/ui_fontsize_rect",
				"type": 0,
				"scalingGrid": false
			}
		],
		"ui_buttons_new/btn_icon_text": [
			{
				"x": -135,
				"y": -60,
				"width": 270,
				"height": 120,
				"scaleX": 9,
				"scaleY": 4,
				"skewX": 0,
				"skewY": 0,
				"rotation": 0,
				"index": 0,
				"id": "hit_area",
				"image": "ui_commons/ui_transparent_rect",
				"type": 0,
				"scalingGrid": false
			},
			{
				"x": -132,
				"y": -17,
				"width": 264,
				"height": 78,
				"scaleX": 1,
				"scaleY": 1,
				"skewX": 0,
				"skewY": 0,
				"rotation": 0,
				"index": 1,
				"id": "_shadow",
				"image": "ui_buttons_new/btn_shadow",
				"type": 0,
				"scalingGrid": true
			},
			{
				"x": -135,
				"y": -54,
				"width": 270,
				"height": 108,
				"scaleX": 1,
				"scaleY": 1,
				"skewX": 0,
				"skewY": 0,
				"rotation": 0,
				"index": 2,
				"id": "background",
				"image": "ui_buttons_new/btn_bg",
				"type": 0,
				"scalingGrid": true
			},
			{
				"x": -39,
				"y": -32,
				"width": 145,
				"height": 64,
				"scaleX": 18.125137329101562,
				"scaleY": 8.000091552734375,
				"skewX": 0,
				"skewY": 0,
				"rotation": 0,
				"index": 3,
				"id": "labelSize",
				"image": "ui_commons/ui_fontsize_rect",
				"type": 0,
				"scalingGrid": false
			},
			{
				"scaleX": 1,
				"scaleY": 1,
				"skewX": 0,
				"skewY": 0,
				"rotation": 0,
				"lineType": "single line",
				"maxCharacters": 0,
				"textType": "dynamic",
				"face": "微软雅黑",
				"size": 44,
				"fillColor": "#ffffff",
				"alignment": "left",
				"letterSpacing": 0,
				"x": -35.25,
				"y": -31.05,
				"width": 141.25,
				"height": 62.05,
				"index": 4,
				"id": "label",
				"type": 1
			},
			{
				"x": -105,
				"y": -35,
				"width": 58,
				"height": 70,
				"scaleX": 7.248291015625,
				"scaleY": 8.749801635742188,
				"skewX": 0,
				"skewY": 0,
				"rotation": 0,
				"index": 5,
				"id": "iconSize",
				"image": "ui_commons/ui_fontsize_rect",
				"type": 0,
				"scalingGrid": false
			}
		]
	}
}